setup.py
trust_patern_ex_forex_next3/__init__.py
trust_patern_ex_forex_next3/trust_patern_ex_forex_next3.py
trust_patern_ex_forex_next3.egg-info/PKG-INFO
trust_patern_ex_forex_next3.egg-info/SOURCES.txt
trust_patern_ex_forex_next3.egg-info/dependency_links.txt
trust_patern_ex_forex_next3.egg-info/not-zip-safe
trust_patern_ex_forex_next3.egg-info/top_level.txt