Metadata-Version: 1.0
Name: trust-patern-ex-forex-next3
Version: 1.20
Summary: trust_patern_ex_forex_next3
Home-page: UNKNOWN
Author: omid
Author-email: UNKNOWN
License: UNKNOWN
Platform: UNKNOWN
